functionExample/__init__.py
functionExample/custom_sklearn.py
FSAE47_Function_Box_Test-0.1.1.dist-info/LICENSE.txt
FSAE47_Function_Box_Test-0.1.1.dist-info/METADATA
FSAE47_Function_Box_Test-0.1.1.dist-info/WHEEL
FSAE47_Function_Box_Test-0.1.1.dist-info/top_level.txt
FSAE47_Function_Box_Test-0.1.1.dist-info/RECORD
