Metadata-Version: 2.1
Name: FSAE47-Function-Box-Test
Version: 0.1.1
Home-page: https://github.com/UOA-FSAE/functionBox
Author: Toby Osborne
Author-email: toby.osborne@fsae.co.nz
License: MIT
Keywords: function box
License-File: LICENSE.txt
Requires-Dist: scikit-learn
